kraken_client-0.2.0.dist-info/METADATA
kraken_client-0.2.0.dist-info/WHEEL
kraken_client/__init__.py
kraken_client/client.py
kraken_client/models.py
kraken_client-0.2.0.dist-info/RECORD
