Metadata-Version: 2.1
Name: kraken_client
Version: 0.2.0
Author-Email: Fisher60 <kyler@abandontech.cloud>
License: MIT
Requires-Python: >=3.11
Requires-Dist: httpx>=0.25.1
